dhf_wrapper/__init__.py
dhf_wrapper/base_client.py
dhf_wrapper/base_dto.py
dhf_wrapper/client.py
dhf_wrapper/exceptions.py
dhf_wrapper/entities/__init__.py
dhf_wrapper/entities/params.py
dhf_wrapper/entities/payment.py
dhf_wrapper/entities/store.py
dhf_wrapper/entities/transaction.py
dhf_sdk-0.0.4.dist-info/LICENSE
dhf_sdk-0.0.4.dist-info/METADATA
dhf_sdk-0.0.4.dist-info/WHEEL
dhf_sdk-0.0.4.dist-info/top_level.txt
dhf_sdk-0.0.4.dist-info/RECORD
