Metadata-Version: 2.1
Name: dhf-sdk
Version: 0.0.4
Summary: API wrapper for DHFinance.
Author: Andrew Svetlov
License: MIT
Project-URL: GitHub, https://github.com/DHFinance
Platform: macOS
Platform: POSIX
Platform: Windows
Classifier: License :: OSI Approved :: BSD License
Classifier: Intended Audience :: Developers
Classifier: Programming Language :: Python :: 3
Classifier: Programming Language :: Python :: 3 :: Only
Classifier: Programming Language :: Python :: 3.6
Classifier: Programming Language :: Python :: 3.7
Classifier: Programming Language :: Python :: 3.8
Classifier: Programming Language :: Python :: 3.9
Classifier: Programming Language :: Python :: 3.10
Classifier: Operating System :: POSIX
Classifier: Operating System :: MacOS :: MacOS X
Classifier: Operating System :: Microsoft :: Windows
Classifier: Environment :: Web Environment
Classifier: Development Status :: 5 - Production/Stable
Requires-Python: >=3.6
License-File: LICENSE
Requires-Dist: requests (>=2.27.1)
Requires-Dist: nose (>=1.3.7)
